pyrser_ai/__init__.py
pyrser_ai/core/__init__.py
pyrser_ai/core/extractors/__init__.py
pyrser_ai/core/extractors/base_extractor.py
pyrser_ai/core/extractors/llama_index_extractor.py
pyrser_ai/core/extractors/prompts/__init__.py
pyrser_ai/core/extractors/prompts/html_parser_prompt.txt
pyrser_ai/core/parsers/__init__.py
pyrser_ai/core/parsers/file/__init__.py
pyrser_ai/core/parsers/file/file_parser.py
pyrser_ai/core/parsers/html/__init__.py
pyrser_ai/core/parsers/html/base_html_parser.py
pyrser_ai/core/parsers/html/dynamic_html_parser.py
pyrser_ai/core/parsers/html/exceptions.py
pyrser_ai/core/parsers/html/static_html_parser.py
pyrser_ai/core/readers/__init__.py
pyrser_ai/core/readers/base_reader.py
pyrser_ai/core/readers/exceptions.py
pyrser_ai/core/readers/llama_parse_reader.py
pyrser_ai-0.2.1.dist-info/METADATA
pyrser_ai-0.2.1.dist-info/WHEEL
pyrser_ai-0.2.1.dist-info/licenses/LICENSE
pyrser_ai-0.2.1.dist-info/RECORD
