Metadata-Version: 2.3
Name: pyrser-ai
Version: 0.2.1
Summary: Turn anything into a pydantic object
Requires-Python: >=3.10
Requires-Dist: aiohttp>=3.10.10
Requires-Dist: beautifulsoup4>=4.12.3
Requires-Dist: fake-useragent>=1.5.1
Requires-Dist: llama-index>=0.11.23
Requires-Dist: llama-parse>=0.5.13
Requires-Dist: lxml>=5.3.0
Requires-Dist: pydantic>=2.9.2
Provides-Extra: full
Requires-Dist: playwright>=1.48.0; extra == 'full'
